qArchSearch/__init__.py
qArchSearch/device.py
qArchSearch/input.py
qArchSearch/output.py
qArchSearch/search.py
qArchSearch/util.py
qArchSearch/devices/__init__.py
qArchSearch/devices/device.py
qArchSearch-1.0.2.dist-info/LICENSE
qArchSearch-1.0.2.dist-info/METADATA
qArchSearch-1.0.2.dist-info/WHEEL
qArchSearch-1.0.2.dist-info/top_level.txt
qArchSearch-1.0.2.dist-info/RECORD
